hellobluenove/__init__.py
hellobluenove-2.0.dist-info/DESCRIPTION.rst
hellobluenove-2.0.dist-info/METADATA
hellobluenove-2.0.dist-info/RECORD
hellobluenove-2.0.dist-info/WHEEL
hellobluenove-2.0.dist-info/metadata.json
hellobluenove-2.0.dist-info/top_level.txt
