Metadata-Version: 2.0
Name: hellobluenove
Version: 2.0
Summary: Simple flask app
Home-page: https://github.com/bluenove/flask-example
Author: Bluenove
Author-email: UNKNOWN
License: UNKNOWN
Platform: UNKNOWN
Requires-Dist: Click (==7.0)
Requires-Dist: Flask (==1.0.2)
Requires-Dist: Jinja2 (==2.10)
Requires-Dist: MarkupSafe (==1.0)
Requires-Dist: Pygments (==2.2.0)
Requires-Dist: Werkzeug (==0.14.1)
Requires-Dist: atomicwrites (==1.2.1)
Requires-Dist: attrs (==18.2.0)
Requires-Dist: bleach (==3.0.1)
Requires-Dist: certifi (==2018.8.24)
Requires-Dist: cffi (==1.11.5)
Requires-Dist: chardet (==3.0.4)
Requires-Dist: cmarkgfm (==0.4.2)
Requires-Dist: docutils (==0.14)
Requires-Dist: funcsigs (==1.0.2)
Requires-Dist: future (==0.16.0)
Requires-Dist: idna (==2.7)
Requires-Dist: itsdangerous (==0.24)
Requires-Dist: more-itertools (==4.3.0)
Requires-Dist: pathlib2 (==2.3.2)
Requires-Dist: pkginfo (==1.4.2)
Requires-Dist: pluggy (==0.7.1)
Requires-Dist: py (==1.6.0)
Requires-Dist: pycparser (==2.19)
Requires-Dist: pytest (==3.8.2)
Requires-Dist: readme-renderer (==22.0)
Requires-Dist: requests (==2.19.1)
Requires-Dist: requests-toolbelt (==0.8.0)
Requires-Dist: scandir (==1.9.0)
Requires-Dist: six (==1.11.0)
Requires-Dist: tqdm (==4.26.0)
Requires-Dist: twine (==1.12.1)
Requires-Dist: urllib3 (==1.23)
Requires-Dist: waitress (==1.1.0)
Requires-Dist: webencodings (==0.5.1)
